[{"line":3,"elements":[{"start_timestamp":"2023-03-14T22:57:30.039Z","line":17,"name":"TC11 kullanici verilen listedeki kullanici isimleri ile giris yapamamali","description":"","id":"us1007-scenario-outline-ile-coklu-negative-login-test;tc11-kullanici-verilen-listedeki-kullanici-isimleri-ile-giris-yapamamali;;2","type":"scenario","keyword":"Scenario Outline","steps":[{"result":{"duration":5577430000,"status":"passed"},"line":7,"name":"kullanici \"qdUrl\" anasayfaya gider","match":{"arguments":[{"val":"\"qdUrl\"","offset":10}],"location":"stepdefinitions.Amazonstepdefinitions.kullaniciAnasayfayaGider(java.lang.String)"},"keyword":"Given "},{"result":{"duration":878524000,"status":"passed"},"line":8,"name":"ilk login linkine tiklar","match":{"location":"stepdefinitions.Qdstepdefinitiond.ilk_login_linkine_tiklar()"},"keyword":"Then "},{"result":{"duration":42564000,"status":"passed"},"line":9,"name":"username olarak examples dan \"Hasan\" girer","match":{"arguments":[{"val":"\"Hasan\"","offset":29}],"location":"stepdefinitions.Qdstepdefinitiond.usernameOlarakExamplesDanGirer(java.lang.String)"},"keyword":"And "},{"result":{"duration":26693000,"status":"passed"},"line":10,"name":"password olarak examples dan \"12344\" girer","match":{"arguments":[{"val":"\"12344\"","offset":29}],"location":"stepdefinitions.Qdstepdefinitiond.passwordOlarakExamplesDanGirer(java.lang.String)"},"keyword":"And "},{"result":{"duration":27071000,"status":"passed"},"line":11,"name":"login butonuna basar","match":{"location":"stepdefinitions.Qdstepdefinitiond.login_butonuna_basar()"},"keyword":"And "},{"result":{"duration":7709000,"status":"passed"},"line":12,"name":"giris yapilamadigini test eder","match":{"location":"stepdefinitions.Qdstepdefinitiond.giris_yapilamadigini_test_eder()"},"keyword":"Then "},{"result":{"duration":111746000,"status":"passed"},"line":13,"name":"sayfayi kapatir","match":{"location":"stepdefinitions.Amazonstepdefinitions.sayfayi_kapatir()"},"keyword":"And "}],"tags":[{"name":"@rapor"}]},{"start_timestamp":"2023-03-14T22:57:36.731Z","line":18,"name":"TC11 kullanici verilen listedeki kullanici isimleri ile giris yapamamali","description":"","id":"us1007-scenario-outline-ile-coklu-negative-login-test;tc11-kullanici-verilen-listedeki-kullanici-isimleri-ile-giris-yapamamali;;3","type":"scenario","keyword":"Scenario Outline","steps":[{"result":{"duration":3446715000,"status":"passed"},"line":7,"name":"kullanici \"qdUrl\" anasayfaya gider","match":{"arguments":[{"val":"\"qdUrl\"","offset":10}],"location":"stepdefinitions.Amazonstepdefinitions.kullaniciAnasayfayaGider(java.lang.String)"},"keyword":"Given "},{"result":{"duration":978352000,"status":"passed"},"line":8,"name":"ilk login linkine tiklar","match":{"location":"stepdefinitions.Qdstepdefinitiond.ilk_login_linkine_tiklar()"},"keyword":"Then "},{"result":{"duration":43610000,"status":"passed"},"line":9,"name":"username olarak examples dan \"Said\" girer","match":{"arguments":[{"val":"\"Said\"","offset":29}],"location":"stepdefinitions.Qdstepdefinitiond.usernameOlarakExamplesDanGirer(java.lang.String)"},"keyword":"And "},{"result":{"duration":26064000,"status":"passed"},"line":10,"name":"password olarak examples dan \"645363\" girer","match":{"arguments":[{"val":"\"645363\"","offset":29}],"location":"stepdefinitions.Qdstepdefinitiond.passwordOlarakExamplesDanGirer(java.lang.String)"},"keyword":"And "},{"result":{"error_message":"org.openqa.selenium.ElementClickInterceptedException: element click intercepted: Element <button type=\"submit\" class=\"btn red radius-5 mt-4 w-100\">...</button> is not clickable at point (1050, 541). Other element would receive the click: <p>...</p>\n  (Session info: chrome=111.0.5563.64)\nBuild info: version: '4.8.0', revision: '267030adea'\nSystem info: os.name: 'Mac OS X', os.arch: 'aarch64', os.version: '12.6.3', java.version: '11.0.18'\nDriver info: org.openqa.selenium.chrome.ChromeDriver\nCommand: [3e7ae6448365d3bf2620f5a6f815cb1b, clickElement {id=26a45968-da15-438d-97a4-770ad6b2ddd2}]\nCapabilities {acceptInsecureCerts: false, browserName: chrome, browserVersion: 111.0.5563.64, chrome: {chromedriverVersion: 111.0.5563.64 (c710e93d5b63..., userDataDir: /var/folders/hr/zj84595n5x1...}, goog:chromeOptions: {debuggerAddress: localhost:52108}, networkConnectionEnabled: false, pageLoadStrategy: normal, platformName: MAC, proxy: Proxy(), se:cdp: ws://localhost:52108/devtoo..., se:cdpVersion: 111.0.5563.64, setWindowRect: true, strictFileInteractability: false, timeouts: {implicit: 0, pageLoad: 300000, script: 30000}, unhandledPromptBehavior: dismiss and notify, webauthn:extension:credBlob: true, webauthn:extension:largeBlob: true, webauthn:extension:minPinLength: true, webauthn:extension:prf: true, webauthn:virtualAuthenticators: true}\nElement: [[ChromeDriver: chrome on MAC (3e7ae6448365d3bf2620f5a6f815cb1b)] -> xpath: //button[text()='Login']]\nSession ID: 3e7ae6448365d3bf2620f5a6f815cb1b\n\tat java.base/jdk.internal.reflect.NativeConstructorAccessorImpl.newInstance0(Native Method)\n\tat java.base/jdk.internal.reflect.NativeConstructorAccessorImpl.newInstance(NativeConstructorAccessorImpl.java:62)\n\tat java.base/jdk.internal.reflect.DelegatingConstructorAccessorImpl.newInstance(DelegatingConstructorAccessorImpl.java:45)\n\tat java.base/java.lang.reflect.Constructor.newInstance(Constructor.java:490)\n\tat org.openqa.selenium.remote.codec.w3c.W3CHttpResponseCodec.createException(W3CHttpResponseCodec.java:200)\n\tat org.openqa.selenium.remote.codec.w3c.W3CHttpResponseCodec.decode(W3CHttpResponseCodec.java:133)\n\tat org.openqa.selenium.remote.codec.w3c.W3CHttpResponseCodec.decode(W3CHttpResponseCodec.java:53)\n\tat org.openqa.selenium.remote.HttpCommandExecutor.execute(HttpCommandExecutor.java:184)\n\tat org.openqa.selenium.remote.service.DriverCommandExecutor.invokeExecute(DriverCommandExecutor.java:167)\n\tat org.openqa.selenium.remote.service.DriverCommandExecutor.execute(DriverCommandExecutor.java:142)\n\tat org.openqa.selenium.remote.RemoteWebDriver.execute(RemoteWebDriver.java:543)\n\tat org.openqa.selenium.remote.RemoteWebElement.execute(RemoteWebElement.java:257)\n\tat org.openqa.selenium.remote.RemoteWebElement.click(RemoteWebElement.java:78)\n\tat java.base/jdk.internal.reflect.NativeMethodAccessorImpl.invoke0(Native Method)\n\tat java.base/jdk.internal.reflect.NativeMethodAccessorImpl.invoke(NativeMethodAccessorImpl.java:62)\n\tat java.base/jdk.internal.reflect.DelegatingMethodAccessorImpl.invoke(DelegatingMethodAccessorImpl.java:43)\n\tat java.base/java.lang.reflect.Method.invoke(Method.java:566)\n\tat org.openqa.selenium.support.pagefactory.internal.LocatingElementHandler.invoke(LocatingElementHandler.java:52)\n\tat com.sun.proxy.$Proxy22.click(Unknown Source)\n\tat stepdefinitions.Qdstepdefinitiond.login_butonuna_basar(Qdstepdefinitiond.java:25)\n\tat ✽.login butonuna basar(file:///Users/bektas/IdeaProjects/CucumberFrameWork/src/test/resources/features/US1007.feature:11)\n","duration":1083203000,"status":"failed"},"line":11,"name":"login butonuna basar","match":{"location":"stepdefinitions.Qdstepdefinitiond.login_butonuna_basar()"},"keyword":"And "},{"result":{"duration":105000,"status":"skipped"},"line":12,"name":"giris yapilamadigini test eder","match":{"location":"stepdefinitions.Qdstepdefinitiond.giris_yapilamadigini_test_eder()"},"keyword":"Then "},{"result":{"duration":88000,"status":"skipped"},"line":13,"name":"sayfayi kapatir","match":{"location":"stepdefinitions.Amazonstepdefinitions.sayfayi_kapatir()"},"keyword":"And "}],"tags":[{"name":"@rapor"}]},{"start_timestamp":"2023-03-14T22:57:42.329Z","line":19,"name":"TC11 kullanici verilen listedeki kullanici isimleri ile giris yapamamali","description":"","id":"us1007-scenario-outline-ile-coklu-negative-login-test;tc11-kullanici-verilen-listedeki-kullanici-isimleri-ile-giris-yapamamali;;4","type":"scenario","keyword":"Scenario Outline","steps":[{"result":{"duration":1273312000,"status":"passed"},"line":7,"name":"kullanici \"qdUrl\" anasayfaya gider","match":{"arguments":[{"val":"\"qdUrl\"","offset":10}],"location":"stepdefinitions.Amazonstepdefinitions.kullaniciAnasayfayaGider(java.lang.String)"},"keyword":"Given "},{"result":{"duration":339969000,"status":"passed"},"line":8,"name":"ilk login linkine tiklar","match":{"location":"stepdefinitions.Qdstepdefinitiond.ilk_login_linkine_tiklar()"},"keyword":"Then "},{"result":{"duration":23595000,"status":"passed"},"line":9,"name":"username olarak examples dan \"Eyup\" girer","match":{"arguments":[{"val":"\"Eyup\"","offset":29}],"location":"stepdefinitions.Qdstepdefinitiond.usernameOlarakExamplesDanGirer(java.lang.String)"},"keyword":"And "},{"result":{"duration":25330000,"status":"passed"},"line":10,"name":"password olarak examples dan \"jskdbvk\" girer","match":{"arguments":[{"val":"\"jskdbvk\"","offset":29}],"location":"stepdefinitions.Qdstepdefinitiond.passwordOlarakExamplesDanGirer(java.lang.String)"},"keyword":"And "},{"result":{"duration":23706000,"status":"passed"},"line":11,"name":"login butonuna basar","match":{"location":"stepdefinitions.Qdstepdefinitiond.login_butonuna_basar()"},"keyword":"And "},{"result":{"duration":7061000,"status":"passed"},"line":12,"name":"giris yapilamadigini test eder","match":{"location":"stepdefinitions.Qdstepdefinitiond.giris_yapilamadigini_test_eder()"},"keyword":"Then "},{"result":{"duration":116158000,"status":"passed"},"line":13,"name":"sayfayi kapatir","match":{"location":"stepdefinitions.Amazonstepdefinitions.sayfayi_kapatir()"},"keyword":"And "}],"tags":[{"name":"@rapor"}]},{"start_timestamp":"2023-03-14T22:57:44.143Z","line":20,"name":"TC11 kullanici verilen listedeki kullanici isimleri ile giris yapamamali","description":"","id":"us1007-scenario-outline-ile-coklu-negative-login-test;tc11-kullanici-verilen-listedeki-kullanici-isimleri-ile-giris-yapamamali;;5","type":"scenario","keyword":"Scenario Outline","steps":[{"result":{"duration":3798680000,"status":"passed"},"line":7,"name":"kullanici \"qdUrl\" anasayfaya gider","match":{"arguments":[{"val":"\"qdUrl\"","offset":10}],"location":"stepdefinitions.Amazonstepdefinitions.kullaniciAnasayfayaGider(java.lang.String)"},"keyword":"Given "},{"result":{"duration":833903000,"status":"passed"},"line":8,"name":"ilk login linkine tiklar","match":{"location":"stepdefinitions.Qdstepdefinitiond.ilk_login_linkine_tiklar()"},"keyword":"Then "},{"result":{"duration":42476000,"status":"passed"},"line":9,"name":"username olarak examples dan \"Fidan\" girer","match":{"arguments":[{"val":"\"Fidan\"","offset":29}],"location":"stepdefinitions.Qdstepdefinitiond.usernameOlarakExamplesDanGirer(java.lang.String)"},"keyword":"And "},{"result":{"duration":27227000,"status":"passed"},"line":10,"name":"password olarak examples dan \"ytefv86\" girer","match":{"arguments":[{"val":"\"ytefv86\"","offset":29}],"location":"stepdefinitions.Qdstepdefinitiond.passwordOlarakExamplesDanGirer(java.lang.String)"},"keyword":"And "},{"result":{"duration":25892000,"status":"passed"},"line":11,"name":"login butonuna basar","match":{"location":"stepdefinitions.Qdstepdefinitiond.login_butonuna_basar()"},"keyword":"And "},{"result":{"duration":6592000,"status":"passed"},"line":12,"name":"giris yapilamadigini test eder","match":{"location":"stepdefinitions.Qdstepdefinitiond.giris_yapilamadigini_test_eder()"},"keyword":"Then "},{"result":{"duration":113267000,"status":"passed"},"line":13,"name":"sayfayi kapatir","match":{"location":"stepdefinitions.Amazonstepdefinitions.sayfayi_kapatir()"},"keyword":"And "}],"tags":[{"name":"@rapor"}]}],"name":"US1007 Scenario Outline ile coklu negative login test","description":"","id":"us1007-scenario-outline-ile-coklu-negative-login-test","keyword":"Feature","uri":"file:src/test/resources/features/US1007.feature","tags":[]}]